bob/__init__.py
bob/bio/__init__.py
bob/bio/video/__init__.py
bob/bio/video/annotator.py
bob/bio/video/transformer.py
bob/bio/video/utils.py
bob/bio/video/config/__init__.py
bob/bio/video/config/video_wrapper.py
bob/bio/video/config/database/__init__.py
bob/bio/video/config/database/youtube.py
bob/bio/video/database/__init__.py
bob/bio/video/database/database.py
bob/bio/video/database/youtube.py
bob.bio.video-7.0.1.dist-info/LICENSE
bob.bio.video-7.0.1.dist-info/METADATA
bob.bio.video-7.0.1.dist-info/WHEEL
bob.bio.video-7.0.1.dist-info/entry_points.txt
bob.bio.video-7.0.1.dist-info/top_level.txt
bob.bio.video-7.0.1.dist-info/RECORD
